README.txt
quipu.py
setup.py
quipu.egg-info/PKG-INFO
quipu.egg-info/SOURCES.txt
quipu.egg-info/dependency_links.txt
quipu.egg-info/top_level.txt
quipu.egg-info/zip-safe