Metadata-Version: 1.0
Name: quipu
Version: 0.1
Summary: Quipu
